authlete/__init__.py
authlete/api/__init__.py
authlete/api/authlete_api.py
authlete/api/authlete_api_exception.py
authlete/api/authlete_api_impl.py
authlete/api/settings.py
authlete/aws/__init__.py
authlete/aws/arn.py
authlete/aws/apigateway/__init__.py
authlete/aws/apigateway/authorizer.py
authlete/conf/__init__.py
authlete/conf/authlete_configuration.py
authlete/conf/authlete_env_configuration.py
authlete/conf/authlete_ini_configuration.py
authlete/dto/__init__.py
authlete/dto/access_token.py
authlete/dto/address.py
authlete/dto/api_response.py
authlete/dto/authorization_action.py
authlete/dto/authorization_fail_action.py
authlete/dto/authorization_fail_reason.py
authlete/dto/authorization_fail_request.py
authlete/dto/authorization_fail_response.py
authlete/dto/authorization_issue_action.py
authlete/dto/authorization_issue_request.py
authlete/dto/authorization_issue_response.py
authlete/dto/authorization_request.py
authlete/dto/authorization_response.py
authlete/dto/authorization_ticket_info.py
authlete/dto/authorization_ticket_info_action.py
authlete/dto/authorization_ticket_info_request.py
authlete/dto/authorization_ticket_info_response.py
authlete/dto/authorization_ticket_update_action.py
authlete/dto/authorization_ticket_update_request.py
authlete/dto/authorization_ticket_update_response.py
authlete/dto/authorized_client_list_response.py
authlete/dto/authz_details.py
authlete/dto/authz_details_element.py
authlete/dto/backchannel_authentication_action.py
authlete/dto/backchannel_authentication_complete_action.py
authlete/dto/backchannel_authentication_complete_request.py
authlete/dto/backchannel_authentication_complete_response.py
authlete/dto/backchannel_authentication_complete_result.py
authlete/dto/backchannel_authentication_fail_action.py
authlete/dto/backchannel_authentication_fail_reason.py
authlete/dto/backchannel_authentication_fail_request.py
authlete/dto/backchannel_authentication_fail_response.py
authlete-1.3.0.dist-info/METADATA
authlete-1.3.0.dist-info/WHEEL
authlete-1.3.0.dist-info/licenses/LICENSE
authlete-1.3.0.dist-info/RECORD
